README.rst
dbapi20.py
setup.py
dbapi_compliance.egg-info/PKG-INFO
dbapi_compliance.egg-info/SOURCES.txt
dbapi_compliance.egg-info/dependency_links.txt
dbapi_compliance.egg-info/top_level.txt