Metadata-Version: 1.1
Name: dbapi-compliance
Version: 1.15.0
Summary: Python DB API 2.0 driver compliance unit test suite.
Home-page: https://github.com/baztian/dbapi-compliance
Author: Stuart Bishop
Author-email: stuart@stuartbishop.net
License: PD
Platform: UNKNOWN
Classifier: Development Status :: 5 - Production/Stable
Classifier: Intended Audience :: Developers
Classifier: Natural Language :: English
Classifier: License :: Public Domain
Classifier: Operating System :: OS Independent
Classifier: Programming Language :: Python
Classifier: Programming Language :: Python :: 2
Classifier: Programming Language :: Python :: 2.6
Classifier: Programming Language :: Python :: 2.7
Classifier: Programming Language :: Python :: 3
Classifier: Programming Language :: Python :: 3.3
Classifier: Programming Language :: Python :: 3.4
Classifier: Topic :: Software Development :: Libraries :: Python Modules
